pycheck_domain/__init__.py
pycheck_domain/check_domain.py
pycheck_domain-1.0.1.dist-info/LICENSE
pycheck_domain-1.0.1.dist-info/METADATA
pycheck_domain-1.0.1.dist-info/WHEEL
pycheck_domain-1.0.1.dist-info/top_level.txt
pycheck_domain-1.0.1.dist-info/zip-safe
pycheck_domain-1.0.1.dist-info/RECORD
