Metadata-Version: 2.1
Name: pycheck_domain
Version: 1.0.1
Summary: 域名助手
Home-page: https://github.com/buyfakett
Author: buyfakett
Author-email: buyfakett@vip.qq.com
License: MIT
Requires-Python: >=3.6
License-File: LICENSE
Requires-Dist: dnspython
Requires-Dist: pyOpenSSL
